asterisk_utils-0.1.3.416.1804.dist-info/licenses/LICENSE
asteriskutils/__init__.py
asteriskutils/asterisk.json
asteriskutils/calendar.py
asteriskutils/error.py
asteriskutils/log.config
asteriskutils/logo.attpl
asteriskutils/mail.py
asteriskutils/setting.py
asteriskutils/title.attpl
asteriskutils/tools.py
asterisk_utils-0.1.3.416.1804.dist-info/METADATA
asterisk_utils-0.1.3.416.1804.dist-info/WHEEL
asterisk_utils-0.1.3.416.1804.dist-info/top_level.txt
asterisk_utils-0.1.3.416.1804.dist-info/RECORD
