Metadata-Version: 2.4
Name: asterisk-utils
Version: 0.1.3.416.1804
Summary: Utility tools for asterisk series.
Author: Shan,Tian
Author-email: geoshan@163.com
License: Apache License 2.0
Keywords: tools,email,print with log,asterisk
Platform: Independent
Classifier: Development Status :: 4 - Beta
Classifier: Topic :: Utilities
Classifier: License :: OSI Approved :: Apache Software License
Classifier: Environment :: Console
Classifier: Intended Audience :: Developers
Classifier: Operating System :: OS Independent
Classifier: Programming Language :: Python :: 3 :: Only
Classifier: Programming Language :: Python :: 3.10
Requires-Python: >=3.10.0
License-File: LICENSE
Requires-Dist: colorama>=0.4.4
Requires-Dist: Deprecated>=1.2.13
Dynamic: author
Dynamic: author-email
Dynamic: classifier
Dynamic: description
Dynamic: description-content-type
Dynamic: keywords
Dynamic: license
Dynamic: license-file
Dynamic: platform
Dynamic: requires-dist
Dynamic: requires-python
Dynamic: summary
